odoo10_addon_account_cash_discount_base-10.0.1.0.0.99.dev16-py2.7-nspkg.pth
odoo/addons/account_cash_discount_base/README.rst
odoo/addons/account_cash_discount_base/__init__.py
odoo/addons/account_cash_discount_base/__manifest__.py
odoo/addons/account_cash_discount_base/i18n/account_cash_discount_base.pot
odoo/addons/account_cash_discount_base/i18n/fr.po
odoo/addons/account_cash_discount_base/migrations/10.0.1.0.0/pre-migration.py
odoo/addons/account_cash_discount_base/models/__init__.py
odoo/addons/account_cash_discount_base/models/account_invoice.py
odoo/addons/account_cash_discount_base/models/account_payment_term.py
odoo/addons/account_cash_discount_base/models/res_company.py
odoo/addons/account_cash_discount_base/reports/report_invoice.xml
odoo/addons/account_cash_discount_base/static/description/icon.png
odoo/addons/account_cash_discount_base/tests/__init__.py
odoo/addons/account_cash_discount_base/tests/common.py
odoo/addons/account_cash_discount_base/tests/test_account_cash_discount_base.py
odoo/addons/account_cash_discount_base/views/account_invoice.xml
odoo/addons/account_cash_discount_base/views/account_payment_term.xml
odoo/addons/account_cash_discount_base/views/res_company.xml
odoo10_addon_account_cash_discount_base-10.0.1.0.0.99.dev16.dist-info/METADATA
odoo10_addon_account_cash_discount_base-10.0.1.0.0.99.dev16.dist-info/RECORD
odoo10_addon_account_cash_discount_base-10.0.1.0.0.99.dev16.dist-info/WHEEL
odoo10_addon_account_cash_discount_base-10.0.1.0.0.99.dev16.dist-info/namespace_packages.txt
odoo10_addon_account_cash_discount_base-10.0.1.0.0.99.dev16.dist-info/top_level.txt
